{
  "spacing": {
    "stack": {
      "xxxs": { "value": 4, "category": "spacing" },
      "xxs": { "value": 8, "category": "spacing" },
      "xs": { "value": 16, "category": "spacing" },
      "sm": { "value": 24, "category": "spacing" },
      "md": { "value": 40, "category": "spacing" },
      "lg": { "value": 64, "category": "spacing" },
      "xl": { "value": 80, "category": "spacing" },
      "xxl": { "value": 128, "category": "spacing" },
      "xxxl": { "value": 200, "category": "spacing" }
    }
  }
}
